Metadata-Version: 1.0
Name: lgx
Version: 1.0.2
Summary: are you ok?
Home-page: http://www.laoguo.com
Author: laoguo
Author-email: laoguo@126.com
License: UNKNOWN
Platform: UNKNOWN
